psearch/__init__.py
psearch/calc_consensus.py
psearch/matrix_2.py
psearch/multiprofile_screening.py
psearch/prepare_dataset.py
psearch/prepare_db.py
psearch/psearch.py
psearch/stat_consensus_matrix.py
psearch/scripts/__init__.py
psearch/scripts/create_db.py
psearch/scripts/external_statistics.py
psearch/scripts/gen_conf_rdkit.py
psearch/scripts/gen_pharm_models.py
psearch/scripts/gen_stereo_rdkit.py
psearch/scripts/read_input.py
psearch/scripts/screen_db.py
psearch/scripts/select_training_set_rdkit.py
psearch/scripts/split.py
psearch-0.0.4.dist-info/LICENSE.txt
psearch-0.0.4.dist-info/METADATA
psearch-0.0.4.dist-info/WHEEL
psearch-0.0.4.dist-info/entry_points.txt
psearch-0.0.4.dist-info/top_level.txt
psearch-0.0.4.dist-info/RECORD
