Metadata-Version: 2.1
Name: psearch
Version: 0.0.4
Summary: PSearch: ligand-based pharmacophore modeling and screening
Home-page: https://github.com/meddwl/psearch
Author: Alina Kutlushina, Pavel Polishchuk
Author-email: alina.kutlushina@pharminnotech.com, pavel_polishchuk@ukr.net
License: UNKNOWN
Platform: UNKNOWN
Classifier: Programming Language :: Python :: 3
Classifier: License :: OSI Approved :: BSD License
Classifier: Operating System :: OS Independent
Classifier: Topic :: Scientific/Engineering :: Bio-Informatics
Classifier: Topic :: Scientific/Engineering :: Chemistry
Requires-Python: >=3.6
Requires-Dist: pmapper (>=0.3)
